eerepr/__init__.py
eerepr/config.py
eerepr/html.py
eerepr/repr.py
eerepr/static/__init__.py
eerepr/static/css/__init__.py
eerepr/static/css/style.css
eerepr/static/js/__init__.py
eerepr/static/js/script.js
eerepr-0.0.3.dist-info/METADATA
eerepr-0.0.3.dist-info/WHEEL
eerepr-0.0.3.dist-info/licenses/LICENSE
eerepr-0.0.3.dist-info/RECORD
