Metadata-Version: 2.1
Name: eerepr
Version: 0.0.3
Summary: Code Editor-style reprs for Earth Engine data in a Jupyter notebook.
Project-URL: Homepage, https://github.com/aazuspan/eerepr
Author: Aaron Zuspan
License: MIT License
License-File: LICENSE
Keywords: earthengine,gee,html,jupyter,notebook,reprs
Requires-Python: >=3.7
Requires-Dist: earthengine-api
Provides-Extra: dev
Requires-Dist: black; extra == 'dev'
Requires-Dist: hatch; extra == 'dev'
Requires-Dist: ipykernel; extra == 'dev'
Requires-Dist: isort; extra == 'dev'
Requires-Dist: jupyterlab; extra == 'dev'
Requires-Dist: pytest; extra == 'dev'
Requires-Dist: pytest-cov; extra == 'dev'
